pypub/__init__.py
pypub/chapter.py
pypub/clean.py
pypub/constants.py
pypub/epub.py
pypub/profile_tests.py
pypub/unit_tests_chapter.py
pypub/unit_tests_clean.py
pypub/unit_tests_epub.py
pypub/unit_tests_image.py
pypub/epub_templates/container.xml
pypub/epub_templates/minetype.txt
pypub/epub_templates/opf.xml
pypub/epub_templates/toc.html
pypub/epub_templates/toc_ncx.xml
pypub-1.5.dist-info/LICENSE
pypub-1.5.dist-info/METADATA
pypub-1.5.dist-info/WHEEL
pypub-1.5.dist-info/top_level.txt
pypub-1.5.dist-info/RECORD
