Metadata-Version: 2.1
Name: pypub
Version: 1.5
Summary: Create epub's using python. Pypub is a python library to create epub files quickly without having to worry about the intricacies of the epub specification.
Home-page: https://github.com/wcember/pypub
Author: William Cember
Author-email: wcember@gmail.com
License: MIT
Platform: UNKNOWN
Requires-Dist: beautifulsoup4
Requires-Dist: jinja2
Requires-Dist: requests
